.gitignore
LICENSE
MANIFEST.in
README.md
requirements.txt
setup.py
buddy/__init__.py
buddy/buddy.py
chatGPT_buddy.egg-info/PKG-INFO
chatGPT_buddy.egg-info/SOURCES.txt
chatGPT_buddy.egg-info/dependency_links.txt
chatGPT_buddy.egg-info/requires.txt
chatGPT_buddy.egg-info/top_level.txt