Metadata-Version: 2.1
Name: chatGPT-buddy
Version: 0.1
Summary: A voice command tool that uses ChatGPT as NLU
Home-page: UNKNOWN
Author: Khaled Achech
Author-email: achechkhaled@gmail.com
License: UNKNOWN
Platform: UNKNOWN
License-File: LICENSE
